MANIFEST.in
readme.md
setup.py
cmsplugin_twitter/__init__.py
cmsplugin_twitter/cms_plugins.py
cmsplugin_twitter/models.py
cmsplugin_twitter.egg-info/PKG-INFO
cmsplugin_twitter.egg-info/SOURCES.txt
cmsplugin_twitter.egg-info/dependency_links.txt
cmsplugin_twitter.egg-info/not-zip-safe
cmsplugin_twitter.egg-info/top_level.txt
cmsplugin_twitter/migrations/0001_initial.py
cmsplugin_twitter/migrations/__init__.py
cmsplugin_twitter/templates/cmsplugin_twitter/plugin.html