Metadata-Version: 1.0
Name: cmsplugin-twitter
Version: 1.1.0
Summary: Twitter plugin to work with Django-CMS
Home-page: http://github.com/changer/cmsplugin-twitter
Author: Vinit Kumar
Author-email: vinit.kumar@changer.nl
License: UNKNOWN
Platform: UNKNOWN
